langsmith_cli/__init__.py
langsmith_cli/config.py
langsmith_cli/field_analysis.py
langsmith_cli/filters.py
langsmith_cli/logging.py
langsmith_cli/main.py
langsmith_cli/utils.py
langsmith_cli/commands/auth.py
langsmith_cli/commands/datasets.py
langsmith_cli/commands/examples.py
langsmith_cli/commands/projects.py
langsmith_cli/commands/prompts.py
langsmith_cli/commands/runs.py
langsmith_cli-0.2.9.dist-info/METADATA
langsmith_cli-0.2.9.dist-info/WHEEL
langsmith_cli-0.2.9.dist-info/entry_points.txt
langsmith_cli-0.2.9.dist-info/licenses/LICENSE
langsmith_cli-0.2.9.dist-info/RECORD
