Metadata-Version: 2.4
Name: langsmith-cli
Version: 0.2.9
Summary: Context-efficient CLI for LangSmith. Built for humans and agents.
Project-URL: Homepage, https://github.com/aviadr1/langsmith-cli
Project-URL: Repository, https://github.com/aviadr1/langsmith-cli
Project-URL: Issues, https://github.com/aviadr1/langsmith-cli/issues
Project-URL: Documentation, https://github.com/aviadr1/langsmith-cli#readme
Author: Aviad Rozenhek
License: MIT License
License-File: LICENSE
Keywords: ai,cli,debugging,langchain,langsmith,llm,observability,tracing
Classifier: Development Status :: 4 - Beta
Classifier: Intended Audience :: Developers
Classifier: License :: OSI Approved :: MIT License
Classifier: Programming Language :: Python :: 3
Classifier: Programming Language :: Python :: 3.12
Classifier: Topic :: Software Development :: Libraries :: Python Modules
Classifier: Topic :: System :: Monitoring
Requires-Python: >=3.12
Requires-Dist: click>=8.3.1
Requires-Dist: langdetect>=1.0.9
Requires-Dist: langsmith>=0.6.2
Requires-Dist: platformdirs>=4.0
Requires-Dist: pydantic>=2.12.5
Requires-Dist: python-dotenv>=1.2.1
Requires-Dist: pyyaml>=6.0.3
Requires-Dist: rich>=14.2.0
